motile_plugin/__init__.py
motile_plugin/example_data.py
motile_plugin/napari.yaml
motile_plugin/application_menus/__init__.py
motile_plugin/application_menus/editing_menu.py
motile_plugin/application_menus/main_app.py
motile_plugin/application_menus/menu_widget.py
motile_plugin/data_model/__init__.py
motile_plugin/data_model/action_history.py
motile_plugin/data_model/actions.py
motile_plugin/data_model/node_type.py
motile_plugin/data_model/solution_tracks.py
motile_plugin/data_model/tracks.py
motile_plugin/data_model/tracks_controller.py
motile_plugin/data_views/__init__.py
motile_plugin/data_views/views/__init__.py
motile_plugin/data_views/views/layers/__init__.py
motile_plugin/data_views/views/layers/track_graph.py
motile_plugin/data_views/views/layers/track_labels.py
motile_plugin/data_views/views/layers/track_points.py
motile_plugin/data_views/views/layers/tracks_layer_group.py
motile_plugin/data_views/views/tree_view/__init__.py
motile_plugin/data_views/views/tree_view/navigation_widget.py
motile_plugin/data_views/views/tree_view/tree_view_feature_widget.py
motile_plugin/data_views/views/tree_view/tree_view_mode_widget.py
motile_plugin/data_views/views/tree_view/tree_widget.py
motile_plugin/data_views/views/tree_view/tree_widget_utils.py
motile_plugin/data_views/views_coordinator/__init__.py
motile_plugin/data_views/views_coordinator/node_selection_list.py
motile_plugin/data_views/views_coordinator/tracks_list.py
motile_plugin/data_views/views_coordinator/tracks_viewer.py
motile_plugin/motile/backend/__init__.py
motile_plugin/motile/backend/motile_run.py
motile_plugin/motile/backend/solve.py
motile_plugin/motile/backend/solver_params.py
motile_plugin/motile/menus/__init__.py
motile_plugin/motile/menus/motile_widget.py
motile_plugin/motile/menus/param_values.py
motile_plugin/motile/menus/params_editor.py
motile_plugin/motile/menus/params_viewer.py
motile_plugin/motile/menus/run_editor.py
motile_plugin/motile/menus/run_viewer.py
motile_plugin-2.0.1.dist-info/LICENSE
motile_plugin-2.0.1.dist-info/METADATA
motile_plugin-2.0.1.dist-info/WHEEL
motile_plugin-2.0.1.dist-info/entry_points.txt
motile_plugin-2.0.1.dist-info/top_level.txt
motile_plugin-2.0.1.dist-info/RECORD
