Metadata-Version: 2.1
Name: motile-plugin
Version: 2.0.1
Summary: Tracking with motile
Author-email: Caroline Malin-Mayor <malinmayorc@janelia.hhmi.org>
License: BSD 3-Clause License
Project-URL: Bug Tracker, https://github.com/funkelab/motile-napari-plugin/issues
Project-URL: Documentation, https://funkelab.github.io/motile_napari_plugin/
Classifier: Development Status :: 2 - Pre-Alpha
Classifier: Framework :: napari
Classifier: Intended Audience :: Developers
Classifier: License :: OSI Approved :: BSD License
Classifier: Operating System :: OS Independent
Classifier: Programming Language :: Python
Classifier: Programming Language :: Python :: 3
Classifier: Programming Language :: Python :: 3 :: Only
Classifier: Programming Language :: Python :: 3.10
Classifier: Programming Language :: Python :: 3.11
Classifier: Topic :: Scientific/Engineering :: Image Processing
Requires-Python: >=3.10
License-File: LICENSE
Requires-Dist: napari[all]
Requires-Dist: numpy
Requires-Dist: magicgui
Requires-Dist: qtpy
Requires-Dist: scikit-image
Requires-Dist: motile >=0.3
Requires-Dist: motile-toolbox >=0.3.5
Requires-Dist: pydantic
Requires-Dist: tifffile[all]
Requires-Dist: fonticon-fontawesome6
Requires-Dist: pyqtgraph
Requires-Dist: lxml-html-clean
Provides-Extra: docs
Requires-Dist: myst-parser ; extra == 'docs'
Requires-Dist: sphinx ; extra == 'docs'
Requires-Dist: sphinx-autoapi ; extra == 'docs'
Requires-Dist: sphinx-rtd-theme ; extra == 'docs'
Requires-Dist: sphinxcontrib-video ; extra == 'docs'
Provides-Extra: testing
Requires-Dist: napari ; extra == 'testing'
Requires-Dist: pyqt5 ; extra == 'testing'
Requires-Dist: pytest ; extra == 'testing'
Requires-Dist: pytest-cov ; extra == 'testing'
Requires-Dist: pytest-qt ; extra == 'testing'
